MANIFEST.in
README.txt
setup.py
deimos21/__init__.py
deimos21/run21.py
deimos21.egg-info/PKG-INFO
deimos21.egg-info/SOURCES.txt
deimos21.egg-info/dependency_links.txt
deimos21.egg-info/top_level.txt