Metadata-Version: 2.1
Name: deimos21
Version: 0.21
Summary: deimos
Home-page: 
Author: yuvi
Author-email: idkyuvi@protonmail.com
Keywords: deimos
